{
	"meta": {
		"image": "spritesheet.png",
		"size": {"w":1152,"h":952},
		"scale": "1"
	},
	"frames": {
		"mosquito_5.png":
		{
			"frame": {"x":0,"y":0,"w":168,"h":232},
			"rotated": false,
			"trimmed": true,
			"spriteSourceSize": {"x":44,"y":12,"w":168,"h":232},
			"sourceSize": {"w":256,"h":256}
		},
		"croc_2.png":
		{
			"frame": {"x":168,"y":0,"w":232,"h":120},
			"rotated": false,
			"trimmed": true,
			"spriteSourceSize": {"x":12,"y":68,"w":232,"h":120},
			"sourceSize": {"w":256,"h":256}
		},
		"croc_5.png":
		{
			"frame": {"x":0,"y":232,"w":232,"h":120},
			"rotated": false,
			"trimmed": true,
			"spriteSourceSize": {"x":12,"y":68,"w":232,"h":120},
			"sourceSize": {"w":256,"h":256}
		},
		"croc_1.png":
		{
			"frame": {"x":168,"y":120,"w":232,"h":112},
			"rotated": false,
			"trimmed": true,
			"spriteSourceSize": {"x":12,"y":72,"w":232,"h":112},
			"sourceSize": {"w":256,"h":256}
		},
		"croc_3.png":
		{
			"frame": {"x":400,"y":0,"w":232,"h":112},
			"rotated": false,
			"trimmed": true,
			"spriteSourceSize": {"x":12,"y":72,"w":232,"h":112},
			"sourceSize": {"w":256,"h":256}
		},
		"croc_4.png":
		{
			"frame": {"x":400,"y":112,"w":232,"h":112},
			"rotated": false,
			"trimmed": true,
			"spriteSourceSize": {"x":12,"y":72,"w":232,"h":112},
			"sourceSize": {"w":256,"h":256}
		},
		"croc_6.png":
		{
			"frame": {"x":400,"y":224,"w":232,"h":112},
			"rotated": false,
			"trimmed": true,
			"spriteSourceSize": {"x":12,"y":72,"w":232,"h":112},
			"sourceSize": {"w":256,"h":256}
		},
		"croc_7.png":
		{
			"frame": {"x":0,"y":352,"w":232,"h":112},
			"rotated": false,
			"trimmed": true,
			"spriteSourceSize": {"x":12,"y":72,"w":232,"h":112},
			"sourceSize": {"w":256,"h":256}
		},
		"worm_2.png":
		{
			"frame": {"x":232,"y":352,"w":224,"h":64},
			"rotated": false,
			"trimmed": true,
			"spriteSourceSize": {"x":16,"y":96,"w":224,"h":64},
			"sourceSize": {"w":256,"h":256}
		},
		"spaceman_2.png":
		{
			"frame": {"x":0,"y":464,"w":208,"h":144},
			"rotated": false,
			"trimmed": true,
			"spriteSourceSize": {"x":24,"y":56,"w":208,"h":144},
			"sourceSize": {"w":256,"h":256}
		},
		"worm_3.png":
		{
			"frame": {"x":208,"y":464,"w":200,"h":72},
			"rotated": false,
			"trimmed": true,
			"spriteSourceSize": {"x":28,"y":92,"w":200,"h":72},
			"sourceSize": {"w":256,"h":256}
		},
		"orange_1.png":
		{
			"frame": {"x":632,"y":0,"w":192,"h":160},
			"rotated": false,
			"trimmed": true,
			"spriteSourceSize": {"x":32,"y":48,"w":192,"h":160},
			"sourceSize": {"w":256,"h":256}
		},
		"spaceman_1.png":
		{
			"frame": {"x":632,"y":160,"w":192,"h":136},
			"rotated": false,
			"trimmed": true,
			"spriteSourceSize": {"x":32,"y":60,"w":192,"h":136},
			"sourceSize": {"w":256,"h":256}
		},
		"mosquito_1.png":
		{
			"frame": {"x":632,"y":296,"w":184,"h":184},
			"rotated": false,
			"trimmed": true,
			"spriteSourceSize": {"x":36,"y":36,"w":184,"h":184},
			"sourceSize": {"w":256,"h":256}
		},
		"mosquito_2.png":
		{
			"frame": {"x":0,"y":608,"w":184,"h":176},
			"rotated": false,
			"trimmed": true,
			"spriteSourceSize": {"x":36,"y":40,"w":184,"h":176},
			"sourceSize": {"w":256,"h":256}
		},
		"mosquito_6.png":
		{
			"frame": {"x":184,"y":608,"w":184,"h":168},
			"rotated": false,
			"trimmed": true,
			"spriteSourceSize": {"x":36,"y":44,"w":184,"h":168},
			"sourceSize": {"w":256,"h":256}
		},
		"mosquito_4.png":
		{
			"frame": {"x":368,"y":608,"w":184,"h":160},
			"rotated": false,
			"trimmed": true,
			"spriteSourceSize": {"x":36,"y":48,"w":184,"h":160},
			"sourceSize": {"w":256,"h":256}
		},
		"mosquito_3.png":
		{
			"frame": {"x":552,"y":608,"w":184,"h":152},
			"rotated": false,
			"trimmed": true,
			"spriteSourceSize": {"x":36,"y":52,"w":184,"h":152},
			"sourceSize": {"w":256,"h":256}
		},
		"worm_1.png":
		{
			"frame": {"x":632,"y":480,"w":184,"h":88},
			"rotated": false,
			"trimmed": true,
			"spriteSourceSize": {"x":36,"y":84,"w":184,"h":88},
			"sourceSize": {"w":256,"h":256}
		},
		"spaceman_7.png":
		{
			"frame": {"x":824,"y":0,"w":176,"h":152},
			"rotated": false,
			"trimmed": true,
			"spriteSourceSize": {"x":40,"y":52,"w":176,"h":152},
			"sourceSize": {"w":256,"h":256}
		},
		"spaceman_3.png":
		{
			"frame": {"x":824,"y":152,"w":176,"h":144},
			"rotated": false,
			"trimmed": true,
			"spriteSourceSize": {"x":40,"y":56,"w":176,"h":144},
			"sourceSize": {"w":256,"h":256}
		},
		"spaceman_6.png":
		{
			"frame": {"x":824,"y":296,"w":176,"h":144},
			"rotated": false,
			"trimmed": true,
			"spriteSourceSize": {"x":40,"y":56,"w":176,"h":144},
			"sourceSize": {"w":256,"h":256}
		},
		"spaceman_4.png":
		{
			"frame": {"x":824,"y":440,"w":176,"h":136},
			"rotated": false,
			"trimmed": true,
			"spriteSourceSize": {"x":40,"y":60,"w":176,"h":136},
			"sourceSize": {"w":256,"h":256}
		},
		"spaceman_5.png":
		{
			"frame": {"x":824,"y":576,"w":176,"h":136},
			"rotated": false,
			"trimmed": true,
			"spriteSourceSize": {"x":40,"y":60,"w":176,"h":136},
			"sourceSize": {"w":256,"h":256}
		},
		"orange_5.png":
		{
			"frame": {"x":0,"y":784,"w":168,"h":168},
			"rotated": false,
			"trimmed": true,
			"spriteSourceSize": {"x":44,"y":44,"w":168,"h":168},
			"sourceSize": {"w":256,"h":256}
		},
		"orange_6.png":
		{
			"frame": {"x":168,"y":784,"w":168,"h":160},
			"rotated": false,
			"trimmed": true,
			"spriteSourceSize": {"x":44,"y":48,"w":168,"h":160},
			"sourceSize": {"w":256,"h":256}
		},
		"orange_3.png":
		{
			"frame": {"x":1000,"y":0,"w":152,"h":168},
			"rotated": false,
			"trimmed": true,
			"spriteSourceSize": {"x":52,"y":44,"w":152,"h":168},
			"sourceSize": {"w":256,"h":256}
		},
		"orange_4.png":
		{
			"frame": {"x":1000,"y":168,"w":152,"h":168},
			"rotated": false,
			"trimmed": true,
			"spriteSourceSize": {"x":52,"y":44,"w":152,"h":168},
			"sourceSize": {"w":256,"h":256}
		},
		"worm_4.png":
		{
			"frame": {"x":1000,"y":336,"w":88,"h":168},
			"rotated": false,
			"trimmed": true,
			"spriteSourceSize": {"x":84,"y":44,"w":88,"h":168},
			"sourceSize": {"w":256,"h":256}
		},
		"orange_2.png":
		{
			"frame": {"x":1000,"y":504,"w":152,"h":160},
			"rotated": false,
			"trimmed": true,
			"spriteSourceSize": {"x":52,"y":48,"w":152,"h":160},
			"sourceSize": {"w":256,"h":256}
		},
		"orange_7.png":
		{
			"frame": {"x":1000,"y":664,"w":152,"h":160},
			"rotated": false,
			"trimmed": true,
			"spriteSourceSize": {"x":52,"y":48,"w":152,"h":160},
			"sourceSize": {"w":256,"h":256}
		},
		"blob_4.png":
		{
			"frame": {"x":1000,"y":824,"w":96,"h":88},
			"rotated": false,
			"trimmed": true,
			"spriteSourceSize": {"x":80,"y":84,"w":96,"h":88},
			"sourceSize": {"w":256,"h":256}
		},
		"blob_7.png":
		{
			"frame": {"x":232,"y":232,"w":96,"h":80},
			"rotated": false,
			"trimmed": true,
			"spriteSourceSize": {"x":80,"y":88,"w":96,"h":80},
			"sourceSize": {"w":256,"h":256}
		},
		"blob_6.png":
		{
			"frame": {"x":736,"y":608,"w":88,"h":80},
			"rotated": false,
			"trimmed": true,
			"spriteSourceSize": {"x":84,"y":88,"w":88,"h":80},
			"sourceSize": {"w":256,"h":256}
		},
		"blob_8.png":
		{
			"frame": {"x":336,"y":784,"w":88,"h":80},
			"rotated": false,
			"trimmed": true,
			"spriteSourceSize": {"x":84,"y":88,"w":88,"h":80},
			"sourceSize": {"w":256,"h":256}
		},
		"blob_1.png":
		{
			"frame": {"x":424,"y":784,"w":80,"h":80},
			"rotated": false,
			"trimmed": true,
			"spriteSourceSize": {"x":88,"y":88,"w":80,"h":80},
			"sourceSize": {"w":256,"h":256}
		},
		"blob_2.png":
		{
			"frame": {"x":504,"y":784,"w":80,"h":80},
			"rotated": false,
			"trimmed": true,
			"spriteSourceSize": {"x":88,"y":88,"w":80,"h":80},
			"sourceSize": {"w":256,"h":256}
		},
		"blob_3.png":
		{
			"frame": {"x":584,"y":784,"w":80,"h":80},
			"rotated": false,
			"trimmed": true,
			"spriteSourceSize": {"x":88,"y":88,"w":80,"h":80},
			"sourceSize": {"w":256,"h":256}
		},
		"blob_5.png":
		{
			"frame": {"x":664,"y":784,"w":80,"h":80},
			"rotated": false,
			"trimmed": true,
			"spriteSourceSize": {"x":88,"y":88,"w":80,"h":80},
			"sourceSize": {"w":256,"h":256}
		}
	}
}